coderl/__init__.py
coderl/main.py
coderl/utils.py
coderl/attack/__init__.py
coderl/contrib/__init__.py
coderl/contrib/intercode/__init__.py
coderl/contrib/pwntools/__init__.py
coderl/contrib/trl/__init__.py
coderl/db/__init__.py
coderl/defence/__init__.py
code_rl-0.0.9.dist-info/METADATA
code_rl-0.0.9.dist-info/WHEEL
code_rl-0.0.9.dist-info/top_level.txt
code_rl-0.0.9.dist-info/RECORD
