Metadata-Version: 2.1
Name: code-rl
Version: 0.0.9
Summary: Code RL
Home-page: https://github.com/dheerajmpai/code-rl
Author: Dheeraj Pai
Author-email: dheerajmpaicmu@gmail.com
License: MIT
Classifier: Programming Language :: Python :: 3
Classifier: License :: OSI Approved :: MIT License
Classifier: Operating System :: OS Independent
Requires-Dist: gym
Requires-Dist: intercode-bench ==0.1.22
Requires-Dist: langchain ==0.1.3
Requires-Dist: trl ==0.7.10
Requires-Dist: pwntools ==4.11.1
Requires-Dist: faiss-cpu ==1.7.4
Requires-Dist: pymetasploit3 ==1.0.5
Requires-Dist: sqlmap ==1.8
Requires-Dist: llama-index ==0.9.37.post1
Requires-Dist: transformers
